maybe_boolean/__init__.py
tests/test1.py
maybe_bool-1.0.0.dist-info/LICENSE
maybe_bool-1.0.0.dist-info/METADATA
maybe_bool-1.0.0.dist-info/WHEEL
maybe_bool-1.0.0.dist-info/top_level.txt
maybe_bool-1.0.0.dist-info/RECORD
