Metadata-Version: 2.1
Name: maybe-bool
Version: 1.0.0
Summary: Have a boolean value that could evaluate to true or false
Author-email: Carl Furtado <carlzfurtado@gmail.com>
License: The MIT License (MIT)
Project-URL: Homepage, https://github.com/User0332/maybe-boolean
Keywords: boolean,maybe,joke
Requires-Python: >=3.9
License-File: LICENSE
